RCC/D_FF.v
`timescale 1ns / 1ps
//////////////////////////////////////////////////////////////////////////////////
// Company: 
// Engineer: 
// 
// Create Date: 03/11/2026 09:43:50 PM
// Design Name: 
// Module Name: D_FF
// Project Name: 
// Target Devices: 
// Tool Versions: 
// Description: 
// 
// Dependencies: 
// 
// Revision:
// Revision 0.01 - File Created
// Additional Comments:
// 
//////////////////////////////////////////////////////////////////////////////////


module D_FF(
    output reg q,
    input wire d,
    input wire clk,
    input wire reset
    );
    
    
    always @(posedge reset or negedge clk) begin 
        if(reset) begin
            q   <= 1'b0;
        end else begin
            q <= d;
        end
    end
        
endmodule

RCA/T_FF.v
`timescale 1ns / 1ps
//////////////////////////////////////////////////////////////////////////////////
// Company: 
// Engineer: 
// 
// Create Date: 03/11/2026 09:43:50 PM
// Design Name: 
// Module Name: T_FF
// Project Name: 
// Target Devices: 
// Tool Versions: 
// Description: 
// 
// Dependencies: 
// 
// Revision:
// Revision 0.01 - File Created
// Additional Comments:
// 
//////////////////////////////////////////////////////////////////////////////////


module T_FF(
    output q,
    input clk,
    input reset
    );
    
    wire d;
    D_FF dff0(q,d,clk,reset);
    not n1(d,q);
    
endmodule

RCC/ripple_carry_counter.v
`timescale 1ns / 1ps
//////////////////////////////////////////////////////////////////////////////////
// Company: 
// Engineer: 
// 
// Create Date: 03/11/2026 09:43:50 PM
// Design Name: 
// Module Name: ripple_carry_counter
// Project Name: 
// Target Devices: 
// Tool Versions: 
// Description: 
// 
// Dependencies: 
// 
// Revision:
// Revision 0.01 - File Created
// Additional Comments:
// 
//////////////////////////////////////////////////////////////////////////////////


module ripple_carry_counter(
    output [3:0] q,
    input clk,
    input reset
    );
    
    T_FF tff0(q[0],clk,reset);
    T_FF tff1(q[1],q[0],reset);
    T_FF tff2(q[2],q[1],reset);
    T_FF tff3(q[3],q[2],reset);
endmodule

RCA/stimulus.v
`timescale 1ns / 1ps
//////////////////////////////////////////////////////////////////////////////////
// Company: 
// Engineer: 
// 
// Create Date: 03/14/2026 03:44:23 PM
// Design Name: 
// Module Name: stimulus
// Project Name: 
// Target Devices: 
// Tool Versions: 
// Description: 
// 
// Dependencies: 
// 
// Revision:
// Revision 0.01 - File Created
// Additional Comments:
// 
//////////////////////////////////////////////////////////////////////////////////


module stimulus;
    
    reg clk;
    reg reset;
    wire[3:0] q;
    
    ripple_carry_counter r1(q, clk, reset);
    
    initial 
        clk = 1'b0;
    always
        #5 clk = ~clk;
        
    initial
    begin
        // Setup for GTKWave: This creates the "dump" file
        $dumpfile("rca_test.vcd");
        $dumpvars(0, stimulus);
        reset = 1'b1;
        #15 reset = 1'b0;
        #180 reset = 1'b1;
        #10 reset = 1'b0;
        #20 $finish;
    end
           
           
endmodule

RCC/rca_test.vcd
$date
	Sat Mar 21 07:51:06 2026
$end
$version
	Icarus Verilog
$end
$timescale
	1ps
$end
$scope module stimulus $end
$var wire 4 ! q [3:0] $end
$var reg 1 " clk $end
$var reg 1 # reset $end
$scope module r1 $end
$var wire 1 " clk $end
$var wire 1 # reset $end
$var wire 4 $ q [3:0] $end
$scope module tff0 $end
$var wire 1 " clk $end
$var wire 1 % d $end
$var wire 1 # reset $end
$var wire 1 & q $end
$scope module dff0 $end
$var wire 1 " clk $end
$var wire 1 % d $end
$var wire 1 # reset $end
$var reg 1 & q $end
$upscope $end
$upscope $end
$scope module tff1 $end
$var wire 1 ' clk $end
$var wire 1 ( d $end
$var wire 1 # reset $end
$var wire 1 ) q $end
$scope module dff0 $end
$var wire 1 ' clk $end
$var wire 1 ( d $end
$var wire 1 # reset $end
$var reg 1 ) q $end
$upscope $end
$upscope $end
$scope module tff2 $end
$var wire 1 * clk $end
$var wire 1 + d $end
$var wire 1 # reset $end
$var wire 1 , q $end
$scope module dff0 $end
$var wire 1 * clk $end
$var wire 1 + d $end
$var wire 1 # reset $end
$var reg 1 , q $end
$upscope $end
$upscope $end
$scope module tff3 $end
$var wire 1 - clk $end
$var wire 1 . d $end
$var wire 1 # reset $end
$var wire 1 / q $end
$scope module dff0 $end
$var wire 1 - clk $end
$var wire 1 . d $end
$var wire 1 # reset $end
$var reg 1 / q $end
$upscope $end
$upscope $end
$upscope $end
$upscope $end
$enddefinitions $end
$comment Show the parameter values. $end
$dumpall
$end
#0
$dumpvars
0/
1.
0-
0,
1+
0*
0)
1(
0'
0&
1%
b0 $
1#
0"
b0 !
$end
#5000
1"
#10000
0"
#15000
1"
0#
#20000
0%
1'
b1 !
b1 $
1&
0"
#25000
1"
#30000
0(
1*
1)
1%
0'
b10 !
b10 $
0&
0"
#35000
1"
#40000
0%
1'
b11 !
b11 $
1&
0"
#45000
1"
#50000
0+
1-
1,
1(
0*
0)
1%
0'
b100 !
b100 $
0&
0"
#55000
1"
#60000
0%
1'
b101 !
b101 $
1&
0"
#65000
1"
#70000
0(
1*
1)
1%
0'
b110 !
b110 $
0&
0"
#75000
1"
#80000
0%
1'
b111 !
b111 $
1&
0"
#85000
1"
#90000
0.
1/
1+
0-
0,
1(
0*
0)
1%
0'
b1000 !
b1000 $
0&
0"
#95000
1"
#100000
0%
1'
b1001 !
b1001 $
1&
0"
#105000
1"
#110000
0(
1*
1)
1%
0'
b1010 !
b1010 $
0&
0"
#115000
1"
#120000
0%
1'
b1011 !
b1011 $
1&
0"
#125000
1"
#130000
0+
1-
1,
1(
0*
0)
1%
0'
b1100 !
b1100 $
0&
0"
#135000
1"
#140000
0%
1'
b1101 !
b1101 $
1&
0"
#145000
1"
#150000
0(
1*
1)
1%
0'
b1110 !
b1110 $
0&
0"
#155000
1"
#160000
0%
1'
b1111 !
b1111 $
1&
0"
#165000
1"
#170000
1.
0/
1+
0-
0,
1(
0*
0)
1%
0'
b0 !
b0 $
0&
0"
#175000
1"
#180000
0%
1'
b1 !
b1 $
1&
0"
#185000
1"
#190000
0(
1*
1)
1%
0'
b10 !
b10 $
0&
0"
#195000
1(
0*
b0 !
b0 $
0)
1"
1#
#200000
0"
#205000
1"
0#
#210000
0%
1'
b1 !
b1 $
1&
0"
#215000
1"
#220000
0(
1*
1)
1%
0'
b10 !
b10 $
0&
0"
