Module_D/D.v
`timescale 1ns / 1ps
//////////////////////////////////////////////////////////////////////////////////
// Company: 
// Engineer: 
// 
// Create Date: 04/04/2026 09:43:50 PM
// Design Name: 
// Module Name: D Delay
// Project Name: 
// Target Devices: 
// Tool Versions: 
// Description: 
// 
// Dependencies: 
// 
// Revision:
// Revision 0.01 - File Created
// Additional Comments:
// 
//////////////////////////////////////////////////////////////////////////////////


module D(
    output out,
    input a,b,c
    );
    
    wire e;

    //Instantiate primitive gares to build the circuit
    and #(5) a1(e, a, b); //Delay of 5 on gate a1
    or  #(4) o1(out, e,c); //Delay of 4 on gate o1 
        
endmodule

Module_D/stimulus.v
`timescale 1ns / 1ps
//////////////////////////////////////////////////////////////////////////////////
// Company: 
// Engineer: 
// 
// Create Date: 03/14/2026 03:44:23 PM
// Design Name: 
// Module Name: stimulus
// Project Name: 
// Target Devices: 
// Tool Versions: 
// Description: 
// 
// Dependencies: 
// 
// Revision:
// Revision 0.01 - File Created
// Additional Comments:
// 
//////////////////////////////////////////////////////////////////////////////////

// Stimulus Top-level module
module stimulus;
    
    //Declare variables
    reg A,B,C;
    wire OUT;

    //Instantiate the module D 
    D d1(OUT, A, B, C);

    //Stimulate the inputs. Finish the stimulation at 40 time units        
    initial
    begin
        $dumpfile("delay_test.vcd");
        $dumpvars(0, stimulus);

            A=1'b0; B=1'b0; C=1'b0;
        #10 A=1'b1; B=1'b1; C=1'b1;
        #10 A=1'b1; B=1'b0; C=1'b0;
        #20 $finish;
    end
           
           
endmodule

Module_D/delay_test.vcd
$date
	Sat Apr  4 18:06:38 2026
$end
$version
	Icarus Verilog
$end
$timescale
	1ps
$end
$scope module stimulus $end
$var wire 1 ! OUT $end
$var reg 1 " A $end
$var reg 1 # B $end
$var reg 1 $ C $end
$scope module d1 $end
$var wire 1 " a $end
$var wire 1 # b $end
$var wire 1 $ c $end
$var wire 1 % e $end
$var wire 1 ! out $end
$upscope $end
$upscope $end
$enddefinitions $end
$comment Show the parameter values. $end
$dumpall
$end
#0
$dumpvars
x%
0$
0#
0"
x!
$end
#5000
0%
#9000
0!
#10000
1$
1#
1"
#14000
1!
#15000
1%
#20000
0$
0#
#25000
0%
#29000
0!
