Counter/counter.v
module counter (
    input clk,          // Clock signal
    input reset,        // Reset signal
    output reg [3:0] q  // 4-bit output
);

    // This block triggers every time the clock goes from 0 to 1
    always @(posedge clk or posedge reset) begin
        if (reset)
            q <= 4'b0000; // Reset the counter to zero
        else
            q <= q + 1;   // Increment by 1
    end

endmodule

Counter/counter_tb.v
`timescale 1ns / 1ps

module counter_tb;
    reg clk;
    reg reset;
    wire [3:0] q;

    // Instantiate the Unit Under Test (UUT)
    counter uut (
        .clk(clk),
        .reset(reset),
        .q(q)
    );

    // Generate a clock signal (toggles every 5ns)
    always #5 clk = ~clk;

    initial begin
        // Setup for GTKWave: This creates the "dump" file
        $dumpfile("counter_test.vcd");
        $dumpvars(0, counter_tb);

        // Initialize signals
        clk = 0;
        reset = 1;
        #20 reset = 0;  // Release reset after 20ns

        #100 $finish;   // Stop simulation after 100ns
    end
endmodule

Counter/counter_test.vcd
$date
	Fri Feb 27 07:00:18 2026
$end
$version
	Icarus Verilog
$end
$timescale
	1ps
$end
$scope module counter_tb $end
$var wire 4 ! q [3:0] $end
$var reg 1 " clk $end
$var reg 1 # reset $end
$scope module uut $end
$var wire 1 " clk $end
$var wire 1 # reset $end
$var reg 4 $ q [3:0] $end
$upscope $end
$upscope $end
$enddefinitions $end
$comment Show the parameter values. $end
$dumpall
$end
#0
$dumpvars
b0 $
1#
0"
b0 !
$end
#5000
1"
#10000
0"
#15000
1"
#20000
0"
0#
#25000
b1 !
b1 $
1"
#30000
0"
#35000
b10 !
b10 $
1"
#40000
0"
#45000
b11 !
b11 $
1"
#50000
0"
#55000
b100 !
b100 $
1"
#60000
0"
#65000
b101 !
b101 $
1"
#70000
0"
#75000
b110 !
b110 $
1"
#80000
0"
#85000
b111 !
b111 $
1"
#90000
0"
#95000
b1000 !
b1000 $
1"
#100000
0"
#105000
b1001 !
b1001 $
1"
#110000
0"
#115000
b1010 !
b1010 $
1"
